dagdog/dag.py
dagdog/nodes.py
dagdog/state.py
dagdog-0.1.6.dist-info/licenses/LICENSE
demo/project.py
dagdog-0.1.6.dist-info/METADATA
dagdog-0.1.6.dist-info/WHEEL
dagdog-0.1.6.dist-info/top_level.txt
dagdog-0.1.6.dist-info/RECORD
