Metadata-Version: 2.4
Name: dagdog
Version: 0.1.6
Summary: A lightweight DAG system for data analysis dev ops
Author-email: Zach Kurtz <zkurtz@gmail.com>
Project-URL: Source, https://github.com/zkurtz/dagdog
Requires-Python: >=3.10
License-File: LICENSE
Requires-Dist: networkx>=3.3
Requires-Dist: pandas>=2.2.2
Dynamic: license-file
